{"course":{"vid":"14952","uid":"19331","title":"Italienisch A1 \/ TELC Italiano A1","log":"","status":"1","comment":"1","promote":"0","sticky":"0","ds_switch":"","nid":"14951","type":"course","language":"de","created":"1475045231","changed":"1483397249","tnid":"0","translate":"0","revision_timestamp":"1483397249","revision_uid":"15761","body":{"und":[{"value":"<table border=\"0\" cellpadding=\"0\" cellspacing=\"0\" class=\"aufeinenblock\" style=\"width: 100%;\">\r\n\t<caption style=\"text-align: left;\">Auf einen Blick<\/caption>\r\n\t<tbody>\r\n\t\t<tr style=\"vertical-align: top;\">\r\n\t\t\t<th scope=\"row\" style=\"width: 50%;\">Dauer<\/th>\r\n\t\t\t<td style=\"width:50%\">\r\n\t\t\t<p>Abendkurs:&nbsp;25 Wochen mal 3 Lektionen oder 12.5 Wochen mal 6 Lektionen<\/p>\r\n\r\n\t\t\t<p>Samstagskurs: 25 Wochen mal 3 Lektionen<\/p>\r\n\t\t\t<\/td>\r\n\t\t<\/tr>\r\n\t\t<tr style=\"vertical-align: top;\">\r\n\t\t\t<th scope=\"row\">Beginn<\/th>\r\n\t\t\t<td>\r\n\t\t\t<p>4 mal pro Jahr<\/p>\r\n\t\t\t<\/td>\r\n\t\t<\/tr>\r\n\t\t<tr style=\"vertical-align: top;\">\r\n\t\t\t<th scope=\"row\">Unterrichtszeiten<\/th>\r\n\t\t\t<td>\r\n\t\t\t<div>AK Montag: 19.00-21.30 Uhr,<\/div>\r\n\r\n\t\t\t<div>AK intensiv Montag und Mittwoch: 19.00-21.30 Uhr,<\/div>\r\n\r\n\t\t\t<div>Samstagskurs: 09.00-11.30 Uhr<\/div>\r\n\t\t\t<\/td>\r\n\t\t<\/tr>\r\n\t\t<tr style=\"vertical-align: top;\">\r\n\t\t\t<th scope=\"row\">Kosten<\/th>\r\n\t\t\t<td>\r\n\t\t\t<div><a href=\"\/node\/17072\" target=\"_blank\">Preislisten Sprachschule<\/a><\/div>\r\n\t\t\t<\/td>\r\n\t\t<\/tr>\r\n\t<\/tbody>\r\n<\/table>\r\n","summary":"","format":"html","safe_value":"<table border=\"0\" cellpadding=\"0\" cellspacing=\"0\" class=\"aufeinenblock\" style=\"width: 100%;\"><caption style=\"text-align: left;\">Auf einen Blick<\/caption>\n<tbody><tr style=\"vertical-align: top;\"><th scope=\"row\" style=\"width: 50%;\">Dauer<\/th>\n<td style=\"width:50%\">\n<p>Abendkurs:\u00a025 Wochen mal 3 Lektionen oder 12.5 Wochen mal 6 Lektionen<\/p>\n<p>Samstagskurs: 25 Wochen mal 3 Lektionen<\/p>\n<\/td>\n<\/tr><tr style=\"vertical-align: top;\"><th scope=\"row\">Beginn<\/th>\n<td>\n<p>4 mal pro Jahr<\/p>\n<\/td>\n<\/tr><tr style=\"vertical-align: top;\"><th scope=\"row\">Unterrichtszeiten<\/th>\n<td>\n<div>AK Montag: 19.00-21.30 Uhr,<\/div>\n<div>AK intensiv Montag und Mittwoch: 19.00-21.30 Uhr,<\/div>\n<div>Samstagskurs: 09.00-11.30 Uhr<\/div>\n<\/td>\n<\/tr><tr style=\"vertical-align: top;\"><th scope=\"row\">Kosten<\/th>\n<td>\n<div><a href=\"\/node\/17072\" target=\"_blank\">Preislisten Sprachschule<\/a><\/div>\n<\/td>\n<\/tr><\/tbody><\/table>","safe_summary":""}]},"field_internal_id":[],"field_is_module":{"und":[{"value":"0"}]},"field_segment":{"und":[{"tid":"107"}]},"field_teaser_tabs":{"und":[{"value":"31","revision_id":"31"}]},"field_bn_title":[],"field_bn_description":[],"field_bn_related_ids":[],"field_banner_links":[],"field_sort":{"und":[{"value":"-19"}]},"field_fachgebiet":{"und":[{"tid":"110"}]},"field_brochure":{"und":[{"target_id":"14884"}]},"field_search_tags":{"und":[{"value":"Sprachschule, Grundkurs, Aufbaukurs,  Italienisch, Italienischkurs, Italienischschule, Zertifikat, Intensivkurse, Kompaktkurse, Italienischdiplom, Reisesprachkurs, CELI, A2, B1, B2, C1, C2, TELC, Anf\u00e4ngerkurs","format":null,"safe_value":"Sprachschule, Grundkurs, Aufbaukurs,  Italienisch, Italienischkurs, Italienischschule, Zertifikat, Intensivkurse, Kompaktkurse, Italienischdiplom, Reisesprachkurs, CELI, A2, B1, B2, C1, C2, TELC, Anf\u00e4ngerkurs"}]},"field_has_info_events":[],"metatags":{"de":{"description":{"value":"Parliamo italiano! An der H.B.S. Sprachschule lernen Sie Italienisch auf allen Stufen effizient in kleinen Gruppen oder im Privatunterricht!"}}},"rdf_mapping":{"rdftype":["sioc:Item","foaf:Document"],"title":{"predicates":["dc:title"]},"created":{"predicates":["dc:date","dc:created"],"datatype":"xsd:dateTime","callback":"date_iso8601"},"changed":{"predicates":["dc:modified"],"datatype":"xsd:dateTime","callback":"date_iso8601"},"body":{"predicates":["content:encoded"]},"uid":{"predicates":["sioc:has_creator"],"type":"rel"},"name":{"predicates":["foaf:name"]},"comment_count":{"predicates":["sioc:num_replies"],"datatype":"xsd:integer"},"last_activity":{"predicates":["sioc:last_activity_date"],"datatype":"xsd:dateTime","callback":"date_iso8601"}},"path":{"pathauto":"1"},"cid":"0","last_comment_timestamp":"1475045231","last_comment_name":null,"last_comment_uid":"19331","comment_count":"0","name":"Thomas Schiendorfer","picture":"0","data":"a:2:{s:17:\"mimemail_textonly\";i:0;s:7:\"overlay\";i:1;}"},"course_times":{"15660":{"vid":"15661","uid":"19331","title":"1-Spr-I-A1-Startdaten Ab1","log":"","status":"1","comment":"1","promote":"0","sticky":"0","ds_switch":"","nid":"15660","type":"course_times","language":"de","created":"1476109601","changed":"1481296578","tnid":"0","translate":"0","revision_timestamp":"1481296578","revision_uid":"19410","body":{"und":[{"value":"<p>Mo Abend<\/p>\r\n","summary":"","format":"html","safe_value":"<p>Mo Abend<\/p>\n","safe_summary":""}]},"field_course_date":{"und":[{"value":"2017-01-09 00:00:00","value2":"2017-07-03 00:00:00","timezone":"Europe\/Zurich","timezone_db":"Europe\/Zurich","date_type":"datetime"}]},"field_has_fsv":{"und":[{"value":"0"}]},"field_course":{"und":[{"target_id":"14951"}]},"field_location":{"und":[{"target_id":"6687"}]},"field_brutto_price":{"und":[{"value":"1365"}]},"field_netto_price":[],"field_anmeldungs_link":[],"field_template":{"und":[{"value":"default"}]},"field_detailed_price":{"und":[{"value":"<ul>\r\n\t<li>Total Schulgeld f\u00fcr den gesamten Lehrgang: 1365 CHF.<\/li>\r\n<\/ul>\r\n","format":"html","safe_value":"<ul><li>Total Schulgeld f\u00fcr den gesamten Lehrgang: 1365 CHF.<\/li>\n<\/ul>"}]},"field_master_nid":[],"field_study_variant":[],"field_visible_from":[],"rdf_mapping":{"rdftype":["sioc:Item","foaf:Document"],"title":{"predicates":["dc:title"]},"created":{"predicates":["dc:date","dc:created"],"datatype":"xsd:dateTime","callback":"date_iso8601"},"changed":{"predicates":["dc:modified"],"datatype":"xsd:dateTime","callback":"date_iso8601"},"body":{"predicates":["content:encoded"]},"uid":{"predicates":["sioc:has_creator"],"type":"rel"},"name":{"predicates":["foaf:name"]},"comment_count":{"predicates":["sioc:num_replies"],"datatype":"xsd:integer"},"last_activity":{"predicates":["sioc:last_activity_date"],"datatype":"xsd:dateTime","callback":"date_iso8601"}},"path":{"pathauto":"1"},"cid":"0","last_comment_timestamp":"1476109601","last_comment_name":null,"last_comment_uid":"19331","comment_count":"0","name":"Thomas Schiendorfer","picture":"0","data":"a:2:{s:17:\"mimemail_textonly\";i:0;s:7:\"overlay\";i:1;}"},"15663":{"vid":"15664","uid":"19331","title":"1-Spr-I-A1-Startdaten Ab In1","log":"","status":"1","comment":"1","promote":"0","sticky":"0","ds_switch":"","nid":"15663","type":"course_times","language":"de","created":"1476109922","changed":"1481296917","tnid":"0","translate":"0","revision_timestamp":"1481296917","revision_uid":"19410","body":{"und":[{"value":"<p>Mo &amp; Mi Abend<\/p>\r\n","summary":"","format":"html","safe_value":"<p>Mo &amp; Mi Abend<\/p>\n","safe_summary":""}]},"field_course_date":{"und":[{"value":"2017-01-09 00:00:00","value2":"2017-04-10 00:00:00","timezone":"Europe\/Zurich","timezone_db":"Europe\/Zurich","date_type":"datetime"}]},"field_has_fsv":{"und":[{"value":"0"}]},"field_course":{"und":[{"target_id":"14951"}]},"field_location":{"und":[{"target_id":"6687"}]},"field_brutto_price":{"und":[{"value":"1365"}]},"field_netto_price":[],"field_anmeldungs_link":[],"field_template":{"und":[{"value":"default"}]},"field_detailed_price":{"und":[{"value":"<ul>\r\n\t<li>Total Schulgeld f\u00fcr den gesamten Lehrgang: 1365 CHF.<\/li>\r\n<\/ul>\r\n","format":"html","safe_value":"<ul><li>Total Schulgeld f\u00fcr den gesamten Lehrgang: 1365 CHF.<\/li>\n<\/ul>"}]},"field_master_nid":[],"field_study_variant":[],"field_visible_from":[],"rdf_mapping":{"rdftype":["sioc:Item","foaf:Document"],"title":{"predicates":["dc:title"]},"created":{"predicates":["dc:date","dc:created"],"datatype":"xsd:dateTime","callback":"date_iso8601"},"changed":{"predicates":["dc:modified"],"datatype":"xsd:dateTime","callback":"date_iso8601"},"body":{"predicates":["content:encoded"]},"uid":{"predicates":["sioc:has_creator"],"type":"rel"},"name":{"predicates":["foaf:name"]},"comment_count":{"predicates":["sioc:num_replies"],"datatype":"xsd:integer"},"last_activity":{"predicates":["sioc:last_activity_date"],"datatype":"xsd:dateTime","callback":"date_iso8601"}},"path":{"pathauto":"1"},"cid":"0","last_comment_timestamp":"1476109922","last_comment_name":null,"last_comment_uid":"19331","comment_count":"0","name":"Thomas Schiendorfer","picture":"0","data":"a:2:{s:17:\"mimemail_textonly\";i:0;s:7:\"overlay\";i:1;}"},"15665":{"vid":"15666","uid":"19331","title":"1-Spr-I-A1-Startdaten Vm1","log":"","status":"1","comment":"1","promote":"0","sticky":"0","ds_switch":"","nid":"15665","type":"course_times","language":"de","created":"1476110143","changed":"1481297264","tnid":"0","translate":"0","revision_timestamp":"1481297264","revision_uid":"19410","body":{"und":[{"value":"<p>Sa Vormittag<\/p>\r\n","summary":"","format":"html","safe_value":"<p>Sa Vormittag<\/p>\n","safe_summary":""}]},"field_course_date":{"und":[{"value":"2017-01-14 00:00:00","value2":"2017-07-15 00:00:00","timezone":"Europe\/Zurich","timezone_db":"Europe\/Zurich","date_type":"datetime"}]},"field_has_fsv":{"und":[{"value":"0"}]},"field_course":{"und":[{"target_id":"14951"}]},"field_location":{"und":[{"target_id":"6687"}]},"field_brutto_price":{"und":[{"value":"1365"}]},"field_netto_price":[],"field_anmeldungs_link":[],"field_template":{"und":[{"value":"default"}]},"field_detailed_price":{"und":[{"value":"<ul>\r\n\t<li>Total Schulgeld f\u00fcr den gesamten Lehrgang: 1365 CHF.<\/li>\r\n<\/ul>\r\n","format":"html","safe_value":"<ul><li>Total Schulgeld f\u00fcr den gesamten Lehrgang: 1365 CHF.<\/li>\n<\/ul>"}]},"field_master_nid":[],"field_study_variant":[],"field_visible_from":[],"rdf_mapping":{"rdftype":["sioc:Item","foaf:Document"],"title":{"predicates":["dc:title"]},"created":{"predicates":["dc:date","dc:created"],"datatype":"xsd:dateTime","callback":"date_iso8601"},"changed":{"predicates":["dc:modified"],"datatype":"xsd:dateTime","callback":"date_iso8601"},"body":{"predicates":["content:encoded"]},"uid":{"predicates":["sioc:has_creator"],"type":"rel"},"name":{"predicates":["foaf:name"]},"comment_count":{"predicates":["sioc:num_replies"],"datatype":"xsd:integer"},"last_activity":{"predicates":["sioc:last_activity_date"],"datatype":"xsd:dateTime","callback":"date_iso8601"}},"path":{"pathauto":"1"},"cid":"0","last_comment_timestamp":"1476110143","last_comment_name":null,"last_comment_uid":"19331","comment_count":"0","name":"Thomas Schiendorfer","picture":"0","data":"a:2:{s:17:\"mimemail_textonly\";i:0;s:7:\"overlay\";i:1;}"},"16955":{"vid":"16956","uid":"19410","title":" 1-Spr-I-A1-Startdaten Ab2","log":"","status":"1","comment":"1","promote":"0","sticky":"0","ds_switch":"","nid":"16955","type":"course_times","language":"de","created":"1481296641","changed":"1481296641","tnid":"0","translate":"0","revision_timestamp":"1481296641","revision_uid":"19410","body":{"und":[{"value":"<p>Mo Abend<\/p>\r\n","summary":"","format":"html","safe_value":"<p>Mo Abend<\/p>\n","safe_summary":""}]},"field_course_date":{"und":[{"value":"2017-02-06 00:00:00","value2":"2017-09-18 00:00:00","timezone":"Europe\/Zurich","timezone_db":"Europe\/Zurich","date_type":"datetime"}]},"field_has_fsv":{"und":[{"value":"0"}]},"field_course":{"und":[{"target_id":"14951"}]},"field_location":{"und":[{"target_id":"6687"}]},"field_brutto_price":{"und":[{"value":"1365"}]},"field_netto_price":[],"field_anmeldungs_link":[],"field_template":{"und":[{"value":"default"}]},"field_detailed_price":{"und":[{"value":"<ul>\r\n\t<li>Total Schulgeld f\u00fcr den gesamten Lehrgang: 1365 CHF.<\/li>\r\n<\/ul>\r\n","format":"html","safe_value":"<ul><li>Total Schulgeld f\u00fcr den gesamten Lehrgang: 1365 CHF.<\/li>\n<\/ul>"}]},"field_master_nid":[],"field_study_variant":[],"field_visible_from":[],"rdf_mapping":{"rdftype":["sioc:Item","foaf:Document"],"title":{"predicates":["dc:title"]},"created":{"predicates":["dc:date","dc:created"],"datatype":"xsd:dateTime","callback":"date_iso8601"},"changed":{"predicates":["dc:modified"],"datatype":"xsd:dateTime","callback":"date_iso8601"},"body":{"predicates":["content:encoded"]},"uid":{"predicates":["sioc:has_creator"],"type":"rel"},"name":{"predicates":["foaf:name"]},"comment_count":{"predicates":["sioc:num_replies"],"datatype":"xsd:integer"},"last_activity":{"predicates":["sioc:last_activity_date"],"datatype":"xsd:dateTime","callback":"date_iso8601"}},"path":{"pathauto":"1"},"cid":"0","last_comment_timestamp":"1481296641","last_comment_name":null,"last_comment_uid":"19410","comment_count":"0","name":"Aranshi Abraham","picture":"0","data":"a:1:{s:17:\"mimemail_textonly\";i:0;}"},"16956":{"vid":"16957","uid":"19410","title":"  1-Spr-I-A1-Startdaten Ab3","log":"","status":"1","comment":"1","promote":"0","sticky":"0","ds_switch":"","nid":"16956","type":"course_times","language":"de","created":"1481296679","changed":"1481296679","tnid":"0","translate":"0","revision_timestamp":"1481296679","revision_uid":"19410","body":{"und":[{"value":"<p>Mo Abend<\/p>\r\n","summary":"","format":"html","safe_value":"<p>Mo Abend<\/p>\n","safe_summary":""}]},"field_course_date":{"und":[{"value":"2017-03-06 00:00:00","value2":"2017-10-23 00:00:00","timezone":"Europe\/Zurich","timezone_db":"Europe\/Zurich","date_type":"datetime"}]},"field_has_fsv":{"und":[{"value":"0"}]},"field_course":{"und":[{"target_id":"14951"}]},"field_location":{"und":[{"target_id":"6687"}]},"field_brutto_price":{"und":[{"value":"1365"}]},"field_netto_price":[],"field_anmeldungs_link":[],"field_template":{"und":[{"value":"default"}]},"field_detailed_price":{"und":[{"value":"<ul>\r\n\t<li>Total Schulgeld f\u00fcr den gesamten Lehrgang: 1365 CHF.<\/li>\r\n<\/ul>\r\n","format":"html","safe_value":"<ul><li>Total Schulgeld f\u00fcr den gesamten Lehrgang: 1365 CHF.<\/li>\n<\/ul>"}]},"field_master_nid":[],"field_study_variant":[],"field_visible_from":[],"rdf_mapping":{"rdftype":["sioc:Item","foaf:Document"],"title":{"predicates":["dc:title"]},"created":{"predicates":["dc:date","dc:created"],"datatype":"xsd:dateTime","callback":"date_iso8601"},"changed":{"predicates":["dc:modified"],"datatype":"xsd:dateTime","callback":"date_iso8601"},"body":{"predicates":["content:encoded"]},"uid":{"predicates":["sioc:has_creator"],"type":"rel"},"name":{"predicates":["foaf:name"]},"comment_count":{"predicates":["sioc:num_replies"],"datatype":"xsd:integer"},"last_activity":{"predicates":["sioc:last_activity_date"],"datatype":"xsd:dateTime","callback":"date_iso8601"}},"path":{"pathauto":"1"},"cid":"0","last_comment_timestamp":"1481296679","last_comment_name":null,"last_comment_uid":"19410","comment_count":"0","name":"Aranshi Abraham","picture":"0","data":"a:1:{s:17:\"mimemail_textonly\";i:0;}"},"16957":{"vid":"16958","uid":"19410","title":"   1-Spr-I-A1-Startdaten Ab4","log":"","status":"1","comment":"1","promote":"0","sticky":"0","ds_switch":"","nid":"16957","type":"course_times","language":"de","created":"1481296720","changed":"1481296720","tnid":"0","translate":"0","revision_timestamp":"1481296720","revision_uid":"19410","body":{"und":[{"value":"<p>Mo Abend<\/p>\r\n","summary":"","format":"html","safe_value":"<p>Mo Abend<\/p>\n","safe_summary":""}]},"field_course_date":{"und":[{"value":"2017-04-03 00:00:00","value2":"2017-11-20 00:00:00","timezone":"Europe\/Zurich","timezone_db":"Europe\/Zurich","date_type":"datetime"}]},"field_has_fsv":{"und":[{"value":"0"}]},"field_course":{"und":[{"target_id":"14951"}]},"field_location":{"und":[{"target_id":"6687"}]},"field_brutto_price":{"und":[{"value":"1365"}]},"field_netto_price":[],"field_anmeldungs_link":[],"field_template":{"und":[{"value":"default"}]},"field_detailed_price":{"und":[{"value":"<ul>\r\n\t<li>Total Schulgeld f\u00fcr den gesamten Lehrgang: 1365 CHF.<\/li>\r\n<\/ul>\r\n","format":"html","safe_value":"<ul><li>Total Schulgeld f\u00fcr den gesamten Lehrgang: 1365 CHF.<\/li>\n<\/ul>"}]},"field_master_nid":[],"field_study_variant":[],"field_visible_from":[],"rdf_mapping":{"rdftype":["sioc:Item","foaf:Document"],"title":{"predicates":["dc:title"]},"created":{"predicates":["dc:date","dc:created"],"datatype":"xsd:dateTime","callback":"date_iso8601"},"changed":{"predicates":["dc:modified"],"datatype":"xsd:dateTime","callback":"date_iso8601"},"body":{"predicates":["content:encoded"]},"uid":{"predicates":["sioc:has_creator"],"type":"rel"},"name":{"predicates":["foaf:name"]},"comment_count":{"predicates":["sioc:num_replies"],"datatype":"xsd:integer"},"last_activity":{"predicates":["sioc:last_activity_date"],"datatype":"xsd:dateTime","callback":"date_iso8601"}},"path":{"pathauto":"1"},"cid":"0","last_comment_timestamp":"1481296720","last_comment_name":null,"last_comment_uid":"19410","comment_count":"0","name":"Aranshi Abraham","picture":"0","data":"a:1:{s:17:\"mimemail_textonly\";i:0;}"},"16958":{"vid":"16959","uid":"19410","title":"  1-Spr-I-A1-Startdaten Ab5","log":"","status":"1","comment":"1","promote":"0","sticky":"0","ds_switch":"","nid":"16958","type":"course_times","language":"de","created":"1481296761","changed":"1481296761","tnid":"0","translate":"0","revision_timestamp":"1481296761","revision_uid":"19410","body":{"und":[{"value":"<p>Mo Abend<\/p>\r\n","summary":"","format":"html","safe_value":"<p>Mo Abend<\/p>\n","safe_summary":""}]},"field_course_date":{"und":[{"value":"2017-05-01 00:00:00","value2":"2017-12-18 00:00:00","timezone":"Europe\/Zurich","timezone_db":"Europe\/Zurich","date_type":"datetime"}]},"field_has_fsv":{"und":[{"value":"0"}]},"field_course":{"und":[{"target_id":"14951"}]},"field_location":{"und":[{"target_id":"6687"}]},"field_brutto_price":{"und":[{"value":"1365"}]},"field_netto_price":[],"field_anmeldungs_link":[],"field_template":{"und":[{"value":"default"}]},"field_detailed_price":{"und":[{"value":"<ul>\r\n\t<li>Total Schulgeld f\u00fcr den gesamten Lehrgang: 1365 CHF.<\/li>\r\n<\/ul>\r\n","format":"html","safe_value":"<ul><li>Total Schulgeld f\u00fcr den gesamten Lehrgang: 1365 CHF.<\/li>\n<\/ul>"}]},"field_master_nid":[],"field_study_variant":[],"field_visible_from":[],"rdf_mapping":{"rdftype":["sioc:Item","foaf:Document"],"title":{"predicates":["dc:title"]},"created":{"predicates":["dc:date","dc:created"],"datatype":"xsd:dateTime","callback":"date_iso8601"},"changed":{"predicates":["dc:modified"],"datatype":"xsd:dateTime","callback":"date_iso8601"},"body":{"predicates":["content:encoded"]},"uid":{"predicates":["sioc:has_creator"],"type":"rel"},"name":{"predicates":["foaf:name"]},"comment_count":{"predicates":["sioc:num_replies"],"datatype":"xsd:integer"},"last_activity":{"predicates":["sioc:last_activity_date"],"datatype":"xsd:dateTime","callback":"date_iso8601"}},"path":{"pathauto":"1"},"cid":"0","last_comment_timestamp":"1481296761","last_comment_name":null,"last_comment_uid":"19410","comment_count":"0","name":"Aranshi Abraham","picture":"0","data":"a:1:{s:17:\"mimemail_textonly\";i:0;}"},"16959":{"vid":"16960","uid":"19410","title":"  1-Spr-I-A1-Startdaten Ab6","log":"","status":"1","comment":"1","promote":"0","sticky":"0","ds_switch":"","nid":"16959","type":"course_times","language":"de","created":"1481296817","changed":"1481296817","tnid":"0","translate":"0","revision_timestamp":"1481296817","revision_uid":"19410","body":{"und":[{"value":"<p>Mo Abend<\/p>\r\n","summary":"","format":"html","safe_value":"<p>Mo Abend<\/p>\n","safe_summary":""}]},"field_course_date":{"und":[{"value":"2017-06-05 00:00:00","value2":"2018-01-29 00:00:00","timezone":"Europe\/Zurich","timezone_db":"Europe\/Zurich","date_type":"datetime"}]},"field_has_fsv":{"und":[{"value":"0"}]},"field_course":{"und":[{"target_id":"14951"}]},"field_location":{"und":[{"target_id":"6687"}]},"field_brutto_price":{"und":[{"value":"1365"}]},"field_netto_price":[],"field_anmeldungs_link":[],"field_template":{"und":[{"value":"default"}]},"field_detailed_price":{"und":[{"value":"<ul>\r\n\t<li>Total Schulgeld f\u00fcr den gesamten Lehrgang: 1365 CHF.<\/li>\r\n<\/ul>\r\n","format":"html","safe_value":"<ul><li>Total Schulgeld f\u00fcr den gesamten Lehrgang: 1365 CHF.<\/li>\n<\/ul>"}]},"field_master_nid":[],"field_study_variant":[],"field_visible_from":[],"rdf_mapping":{"rdftype":["sioc:Item","foaf:Document"],"title":{"predicates":["dc:title"]},"created":{"predicates":["dc:date","dc:created"],"datatype":"xsd:dateTime","callback":"date_iso8601"},"changed":{"predicates":["dc:modified"],"datatype":"xsd:dateTime","callback":"date_iso8601"},"body":{"predicates":["content:encoded"]},"uid":{"predicates":["sioc:has_creator"],"type":"rel"},"name":{"predicates":["foaf:name"]},"comment_count":{"predicates":["sioc:num_replies"],"datatype":"xsd:integer"},"last_activity":{"predicates":["sioc:last_activity_date"],"datatype":"xsd:dateTime","callback":"date_iso8601"}},"path":{"pathauto":"1"},"cid":"0","last_comment_timestamp":"1481296817","last_comment_name":null,"last_comment_uid":"19410","comment_count":"0","name":"Aranshi Abraham","picture":"0","data":"a:1:{s:17:\"mimemail_textonly\";i:0;}"},"16960":{"vid":"16961","uid":"19410","title":" 1-Spr-I-A1-Startdaten Ab In2","log":"","status":"1","comment":"1","promote":"0","sticky":"0","ds_switch":"","nid":"16960","type":"course_times","language":"de","created":"1481296951","changed":"1481296951","tnid":"0","translate":"0","revision_timestamp":"1481296951","revision_uid":"19410","body":{"und":[{"value":"<p>Mo &amp; Mi Abend<\/p>\r\n","summary":"","format":"html","safe_value":"<p>Mo &amp; Mi Abend<\/p>\n","safe_summary":""}]},"field_course_date":{"und":[{"value":"2017-02-06 00:00:00","value2":"2017-05-15 00:00:00","timezone":"Europe\/Zurich","timezone_db":"Europe\/Zurich","date_type":"datetime"}]},"field_has_fsv":{"und":[{"value":"0"}]},"field_course":{"und":[{"target_id":"14951"}]},"field_location":{"und":[{"target_id":"6687"}]},"field_brutto_price":{"und":[{"value":"1365"}]},"field_netto_price":[],"field_anmeldungs_link":[],"field_template":{"und":[{"value":"default"}]},"field_detailed_price":{"und":[{"value":"<ul>\r\n\t<li>Total Schulgeld f\u00fcr den gesamten Lehrgang: 1365 CHF.<\/li>\r\n<\/ul>\r\n","format":"html","safe_value":"<ul><li>Total Schulgeld f\u00fcr den gesamten Lehrgang: 1365 CHF.<\/li>\n<\/ul>"}]},"field_master_nid":[],"field_study_variant":[],"field_visible_from":[],"rdf_mapping":{"rdftype":["sioc:Item","foaf:Document"],"title":{"predicates":["dc:title"]},"created":{"predicates":["dc:date","dc:created"],"datatype":"xsd:dateTime","callback":"date_iso8601"},"changed":{"predicates":["dc:modified"],"datatype":"xsd:dateTime","callback":"date_iso8601"},"body":{"predicates":["content:encoded"]},"uid":{"predicates":["sioc:has_creator"],"type":"rel"},"name":{"predicates":["foaf:name"]},"comment_count":{"predicates":["sioc:num_replies"],"datatype":"xsd:integer"},"last_activity":{"predicates":["sioc:last_activity_date"],"datatype":"xsd:dateTime","callback":"date_iso8601"}},"path":{"pathauto":"1"},"cid":"0","last_comment_timestamp":"1481296951","last_comment_name":null,"last_comment_uid":"19410","comment_count":"0","name":"Aranshi Abraham","picture":"0","data":"a:1:{s:17:\"mimemail_textonly\";i:0;}"},"16961":{"vid":"16962","uid":"19410","title":" 1-Spr-I-A1-Startdaten Ab In3","log":"","status":"1","comment":"1","promote":"0","sticky":"0","ds_switch":"","nid":"16961","type":"course_times","language":"de","created":"1481296992","changed":"1481296992","tnid":"0","translate":"0","revision_timestamp":"1481296992","revision_uid":"19410","body":{"und":[{"value":"<p>Mo &amp; Mi Abend<\/p>\r\n","summary":"","format":"html","safe_value":"<p>Mo &amp; Mi Abend<\/p>\n","safe_summary":""}]},"field_course_date":{"und":[{"value":"2017-03-06 00:00:00","value2":"2017-06-05 00:00:00","timezone":"Europe\/Zurich","timezone_db":"Europe\/Zurich","date_type":"datetime"}]},"field_has_fsv":{"und":[{"value":"0"}]},"field_course":{"und":[{"target_id":"14951"}]},"field_location":{"und":[{"target_id":"6687"}]},"field_brutto_price":{"und":[{"value":"1365"}]},"field_netto_price":[],"field_anmeldungs_link":[],"field_template":{"und":[{"value":"default"}]},"field_detailed_price":{"und":[{"value":"<ul>\r\n\t<li>Total Schulgeld f\u00fcr den gesamten Lehrgang: 1365 CHF.<\/li>\r\n<\/ul>\r\n","format":"html","safe_value":"<ul><li>Total Schulgeld f\u00fcr den gesamten Lehrgang: 1365 CHF.<\/li>\n<\/ul>"}]},"field_master_nid":[],"field_study_variant":[],"field_visible_from":[],"rdf_mapping":{"rdftype":["sioc:Item","foaf:Document"],"title":{"predicates":["dc:title"]},"created":{"predicates":["dc:date","dc:created"],"datatype":"xsd:dateTime","callback":"date_iso8601"},"changed":{"predicates":["dc:modified"],"datatype":"xsd:dateTime","callback":"date_iso8601"},"body":{"predicates":["content:encoded"]},"uid":{"predicates":["sioc:has_creator"],"type":"rel"},"name":{"predicates":["foaf:name"]},"comment_count":{"predicates":["sioc:num_replies"],"datatype":"xsd:integer"},"last_activity":{"predicates":["sioc:last_activity_date"],"datatype":"xsd:dateTime","callback":"date_iso8601"}},"path":{"pathauto":"1"},"cid":"0","last_comment_timestamp":"1481296992","last_comment_name":null,"last_comment_uid":"19410","comment_count":"0","name":"Aranshi Abraham","picture":"0","data":"a:1:{s:17:\"mimemail_textonly\";i:0;}"},"16962":{"vid":"16963","uid":"19410","title":"  1-Spr-I-A1-Startdaten Ab In4","log":"","status":"1","comment":"1","promote":"0","sticky":"0","ds_switch":"","nid":"16962","type":"course_times","language":"de","created":"1481297032","changed":"1481297032","tnid":"0","translate":"0","revision_timestamp":"1481297032","revision_uid":"19410","body":{"und":[{"value":"<p>Mo &amp; Mi Abend<\/p>\r\n","summary":"","format":"html","safe_value":"<p>Mo &amp; Mi Abend<\/p>\n","safe_summary":""}]},"field_course_date":{"und":[{"value":"2017-04-03 00:00:00","value2":"2017-07-03 00:00:00","timezone":"Europe\/Zurich","timezone_db":"Europe\/Zurich","date_type":"datetime"}]},"field_has_fsv":{"und":[{"value":"0"}]},"field_course":{"und":[{"target_id":"14951"}]},"field_location":{"und":[{"target_id":"6687"}]},"field_brutto_price":{"und":[{"value":"1365"}]},"field_netto_price":[],"field_anmeldungs_link":[],"field_template":{"und":[{"value":"default"}]},"field_detailed_price":{"und":[{"value":"<ul>\r\n\t<li>Total Schulgeld f\u00fcr den gesamten Lehrgang: 1365 CHF.<\/li>\r\n<\/ul>\r\n","format":"html","safe_value":"<ul><li>Total Schulgeld f\u00fcr den gesamten Lehrgang: 1365 CHF.<\/li>\n<\/ul>"}]},"field_master_nid":[],"field_study_variant":[],"field_visible_from":[],"rdf_mapping":{"rdftype":["sioc:Item","foaf:Document"],"title":{"predicates":["dc:title"]},"created":{"predicates":["dc:date","dc:created"],"datatype":"xsd:dateTime","callback":"date_iso8601"},"changed":{"predicates":["dc:modified"],"datatype":"xsd:dateTime","callback":"date_iso8601"},"body":{"predicates":["content:encoded"]},"uid":{"predicates":["sioc:has_creator"],"type":"rel"},"name":{"predicates":["foaf:name"]},"comment_count":{"predicates":["sioc:num_replies"],"datatype":"xsd:integer"},"last_activity":{"predicates":["sioc:last_activity_date"],"datatype":"xsd:dateTime","callback":"date_iso8601"}},"path":{"pathauto":"1"},"cid":"0","last_comment_timestamp":"1481297032","last_comment_name":null,"last_comment_uid":"19410","comment_count":"0","name":"Aranshi Abraham","picture":"0","data":"a:1:{s:17:\"mimemail_textonly\";i:0;}"},"16963":{"vid":"16964","uid":"19410","title":"  1-Spr-I-A1-Startdaten Ab In5","log":"","status":"1","comment":"1","promote":"0","sticky":"0","ds_switch":"","nid":"16963","type":"course_times","language":"de","created":"1481297068","changed":"1481297068","tnid":"0","translate":"0","revision_timestamp":"1481297068","revision_uid":"19410","body":{"und":[{"value":"<p>Mo &amp; Mi Abend<\/p>\r\n","summary":"","format":"html","safe_value":"<p>Mo &amp; Mi Abend<\/p>\n","safe_summary":""}]},"field_course_date":{"und":[{"value":"2017-05-01 00:00:00","value2":"2017-09-04 00:00:00","timezone":"Europe\/Zurich","timezone_db":"Europe\/Zurich","date_type":"datetime"}]},"field_has_fsv":{"und":[{"value":"0"}]},"field_course":{"und":[{"target_id":"14951"}]},"field_location":{"und":[{"target_id":"6687"}]},"field_brutto_price":{"und":[{"value":"1365"}]},"field_netto_price":[],"field_anmeldungs_link":[],"field_template":{"und":[{"value":"default"}]},"field_detailed_price":{"und":[{"value":"<ul>\r\n\t<li>Total Schulgeld f\u00fcr den gesamten Lehrgang: 1365 CHF.<\/li>\r\n<\/ul>\r\n","format":"html","safe_value":"<ul><li>Total Schulgeld f\u00fcr den gesamten Lehrgang: 1365 CHF.<\/li>\n<\/ul>"}]},"field_master_nid":[],"field_study_variant":[],"field_visible_from":[],"rdf_mapping":{"rdftype":["sioc:Item","foaf:Document"],"title":{"predicates":["dc:title"]},"created":{"predicates":["dc:date","dc:created"],"datatype":"xsd:dateTime","callback":"date_iso8601"},"changed":{"predicates":["dc:modified"],"datatype":"xsd:dateTime","callback":"date_iso8601"},"body":{"predicates":["content:encoded"]},"uid":{"predicates":["sioc:has_creator"],"type":"rel"},"name":{"predicates":["foaf:name"]},"comment_count":{"predicates":["sioc:num_replies"],"datatype":"xsd:integer"},"last_activity":{"predicates":["sioc:last_activity_date"],"datatype":"xsd:dateTime","callback":"date_iso8601"}},"path":{"pathauto":"1"},"cid":"0","last_comment_timestamp":"1481297068","last_comment_name":null,"last_comment_uid":"19410","comment_count":"0","name":"Aranshi Abraham","picture":"0","data":"a:1:{s:17:\"mimemail_textonly\";i:0;}"},"16964":{"vid":"16965","uid":"19410","title":"   1-Spr-I-A1-Startdaten Ab In6","log":"","status":"1","comment":"1","promote":"0","sticky":"0","ds_switch":"","nid":"16964","type":"course_times","language":"de","created":"1481297198","changed":"1481297198","tnid":"0","translate":"0","revision_timestamp":"1481297198","revision_uid":"19410","body":{"und":[{"value":"<p>Mo &amp; Mi Abend<\/p>\r\n","summary":"","format":"html","safe_value":"<p>Mo &amp; Mi Abend<\/p>\n","safe_summary":""}]},"field_course_date":{"und":[{"value":"2017-06-05 00:00:00","value2":"2017-10-23 00:00:00","timezone":"Europe\/Zurich","timezone_db":"Europe\/Zurich","date_type":"datetime"}]},"field_has_fsv":{"und":[{"value":"0"}]},"field_course":{"und":[{"target_id":"14951"}]},"field_location":{"und":[{"target_id":"6687"}]},"field_brutto_price":{"und":[{"value":"1365"}]},"field_netto_price":[],"field_anmeldungs_link":[],"field_template":{"und":[{"value":"default"}]},"field_detailed_price":{"und":[{"value":"<ul>\r\n\t<li>Total Schulgeld f\u00fcr den gesamten Lehrgang: 1365 CHF.<\/li>\r\n<\/ul>\r\n","format":"html","safe_value":"<ul><li>Total Schulgeld f\u00fcr den gesamten Lehrgang: 1365 CHF.<\/li>\n<\/ul>"}]},"field_master_nid":[],"field_study_variant":[],"field_visible_from":[],"rdf_mapping":{"rdftype":["sioc:Item","foaf:Document"],"title":{"predicates":["dc:title"]},"created":{"predicates":["dc:date","dc:created"],"datatype":"xsd:dateTime","callback":"date_iso8601"},"changed":{"predicates":["dc:modified"],"datatype":"xsd:dateTime","callback":"date_iso8601"},"body":{"predicates":["content:encoded"]},"uid":{"predicates":["sioc:has_creator"],"type":"rel"},"name":{"predicates":["foaf:name"]},"comment_count":{"predicates":["sioc:num_replies"],"datatype":"xsd:integer"},"last_activity":{"predicates":["sioc:last_activity_date"],"datatype":"xsd:dateTime","callback":"date_iso8601"}},"path":{"pathauto":"1"},"cid":"0","last_comment_timestamp":"1481297198","last_comment_name":null,"last_comment_uid":"19410","comment_count":"0","name":"Aranshi Abraham","picture":"0","data":"a:1:{s:17:\"mimemail_textonly\";i:0;}"},"16965":{"vid":"16966","uid":"19410","title":" 1-Spr-I-A1-Startdaten Vm2","log":"","status":"1","comment":"1","promote":"0","sticky":"0","ds_switch":"","nid":"16965","type":"course_times","language":"de","created":"1481297310","changed":"1481297310","tnid":"0","translate":"0","revision_timestamp":"1481297310","revision_uid":"19410","body":{"und":[{"value":"<p>Sa Vormittag<\/p>\r\n","summary":"","format":"html","safe_value":"<p>Sa Vormittag<\/p>\n","safe_summary":""}]},"field_course_date":{"und":[{"value":"2017-02-11 00:00:00","value2":"2017-09-23 00:00:00","timezone":"Europe\/Zurich","timezone_db":"Europe\/Zurich","date_type":"datetime"}]},"field_has_fsv":{"und":[{"value":"0"}]},"field_course":{"und":[{"target_id":"14951"}]},"field_location":{"und":[{"target_id":"6687"}]},"field_brutto_price":{"und":[{"value":"1365"}]},"field_netto_price":[],"field_anmeldungs_link":[],"field_template":{"und":[{"value":"default"}]},"field_detailed_price":{"und":[{"value":"<ul>\r\n\t<li>Total Schulgeld f\u00fcr den gesamten Lehrgang: 1365 CHF.<\/li>\r\n<\/ul>\r\n","format":"html","safe_value":"<ul><li>Total Schulgeld f\u00fcr den gesamten Lehrgang: 1365 CHF.<\/li>\n<\/ul>"}]},"field_master_nid":[],"field_study_variant":[],"field_visible_from":[],"rdf_mapping":{"rdftype":["sioc:Item","foaf:Document"],"title":{"predicates":["dc:title"]},"created":{"predicates":["dc:date","dc:created"],"datatype":"xsd:dateTime","callback":"date_iso8601"},"changed":{"predicates":["dc:modified"],"datatype":"xsd:dateTime","callback":"date_iso8601"},"body":{"predicates":["content:encoded"]},"uid":{"predicates":["sioc:has_creator"],"type":"rel"},"name":{"predicates":["foaf:name"]},"comment_count":{"predicates":["sioc:num_replies"],"datatype":"xsd:integer"},"last_activity":{"predicates":["sioc:last_activity_date"],"datatype":"xsd:dateTime","callback":"date_iso8601"}},"path":{"pathauto":"1"},"cid":"0","last_comment_timestamp":"1481297310","last_comment_name":null,"last_comment_uid":"19410","comment_count":"0","name":"Aranshi Abraham","picture":"0","data":"a:1:{s:17:\"mimemail_textonly\";i:0;}"},"16966":{"vid":"16967","uid":"19410","title":"  1-Spr-I-A1-Startdaten Vm3","log":"","status":"1","comment":"1","promote":"0","sticky":"0","ds_switch":"","nid":"16966","type":"course_times","language":"de","created":"1481297354","changed":"1481297354","tnid":"0","translate":"0","revision_timestamp":"1481297354","revision_uid":"19410","body":{"und":[{"value":"<p>Sa Vormittag<\/p>\r\n","summary":"","format":"html","safe_value":"<p>Sa Vormittag<\/p>\n","safe_summary":""}]},"field_course_date":{"und":[{"value":"2017-03-11 00:00:00","value2":"2017-10-28 00:00:00","timezone":"Europe\/Zurich","timezone_db":"Europe\/Zurich","date_type":"datetime"}]},"field_has_fsv":{"und":[{"value":"0"}]},"field_course":{"und":[{"target_id":"14951"}]},"field_location":{"und":[{"target_id":"6687"}]},"field_brutto_price":{"und":[{"value":"1365"}]},"field_netto_price":[],"field_anmeldungs_link":[],"field_template":{"und":[{"value":"default"}]},"field_detailed_price":{"und":[{"value":"<ul>\r\n\t<li>Total Schulgeld f\u00fcr den gesamten Lehrgang: 1365 CHF.<\/li>\r\n<\/ul>\r\n","format":"html","safe_value":"<ul><li>Total Schulgeld f\u00fcr den gesamten Lehrgang: 1365 CHF.<\/li>\n<\/ul>"}]},"field_master_nid":[],"field_study_variant":[],"field_visible_from":[],"rdf_mapping":{"rdftype":["sioc:Item","foaf:Document"],"title":{"predicates":["dc:title"]},"created":{"predicates":["dc:date","dc:created"],"datatype":"xsd:dateTime","callback":"date_iso8601"},"changed":{"predicates":["dc:modified"],"datatype":"xsd:dateTime","callback":"date_iso8601"},"body":{"predicates":["content:encoded"]},"uid":{"predicates":["sioc:has_creator"],"type":"rel"},"name":{"predicates":["foaf:name"]},"comment_count":{"predicates":["sioc:num_replies"],"datatype":"xsd:integer"},"last_activity":{"predicates":["sioc:last_activity_date"],"datatype":"xsd:dateTime","callback":"date_iso8601"}},"path":{"pathauto":"1"},"cid":"0","last_comment_timestamp":"1481297354","last_comment_name":null,"last_comment_uid":"19410","comment_count":"0","name":"Aranshi Abraham","picture":"0","data":"a:1:{s:17:\"mimemail_textonly\";i:0;}"},"16967":{"vid":"16968","uid":"19410","title":"   1-Spr-I-A1-Startdaten Vm4","log":"","status":"1","comment":"1","promote":"0","sticky":"0","ds_switch":"","nid":"16967","type":"course_times","language":"de","created":"1481297399","changed":"1481297399","tnid":"0","translate":"0","revision_timestamp":"1481297399","revision_uid":"19410","body":{"und":[{"value":"<p>Sa Vormittag<\/p>\r\n","summary":"","format":"html","safe_value":"<p>Sa Vormittag<\/p>\n","safe_summary":""}]},"field_course_date":{"und":[{"value":"2017-04-08 00:00:00","value2":"2017-11-25 00:00:00","timezone":"Europe\/Zurich","timezone_db":"Europe\/Zurich","date_type":"datetime"}]},"field_has_fsv":{"und":[{"value":"0"}]},"field_course":{"und":[{"target_id":"14951"}]},"field_location":{"und":[{"target_id":"6687"}]},"field_brutto_price":{"und":[{"value":"1365"}]},"field_netto_price":[],"field_anmeldungs_link":[],"field_template":{"und":[{"value":"default"}]},"field_detailed_price":{"und":[{"value":"<ul>\r\n\t<li>Total Schulgeld f\u00fcr den gesamten Lehrgang: 1365 CHF.<\/li>\r\n<\/ul>\r\n","format":"html","safe_value":"<ul><li>Total Schulgeld f\u00fcr den gesamten Lehrgang: 1365 CHF.<\/li>\n<\/ul>"}]},"field_master_nid":[],"field_study_variant":[],"field_visible_from":[],"rdf_mapping":{"rdftype":["sioc:Item","foaf:Document"],"title":{"predicates":["dc:title"]},"created":{"predicates":["dc:date","dc:created"],"datatype":"xsd:dateTime","callback":"date_iso8601"},"changed":{"predicates":["dc:modified"],"datatype":"xsd:dateTime","callback":"date_iso8601"},"body":{"predicates":["content:encoded"]},"uid":{"predicates":["sioc:has_creator"],"type":"rel"},"name":{"predicates":["foaf:name"]},"comment_count":{"predicates":["sioc:num_replies"],"datatype":"xsd:integer"},"last_activity":{"predicates":["sioc:last_activity_date"],"datatype":"xsd:dateTime","callback":"date_iso8601"}},"path":{"pathauto":"1"},"cid":"0","last_comment_timestamp":"1481297399","last_comment_name":null,"last_comment_uid":"19410","comment_count":"0","name":"Aranshi Abraham","picture":"0","data":"a:1:{s:17:\"mimemail_textonly\";i:0;}"},"16968":{"vid":"16969","uid":"19410","title":"  1-Spr-I-A1-Startdaten Vm5","log":"","status":"1","comment":"1","promote":"0","sticky":"0","ds_switch":"","nid":"16968","type":"course_times","language":"de","created":"1481297443","changed":"1481297443","tnid":"0","translate":"0","revision_timestamp":"1481297443","revision_uid":"19410","body":{"und":[{"value":"<p>Sa Vormittag<\/p>\r\n","summary":"","format":"html","safe_value":"<p>Sa Vormittag<\/p>\n","safe_summary":""}]},"field_course_date":{"und":[{"value":"2017-05-06 00:00:00","value2":"2017-12-23 00:00:00","timezone":"Europe\/Zurich","timezone_db":"Europe\/Zurich","date_type":"datetime"}]},"field_has_fsv":{"und":[{"value":"0"}]},"field_course":{"und":[{"target_id":"14951"}]},"field_location":{"und":[{"target_id":"6687"}]},"field_brutto_price":{"und":[{"value":"1365"}]},"field_netto_price":[],"field_anmeldungs_link":[],"field_template":{"und":[{"value":"default"}]},"field_detailed_price":{"und":[{"value":"<ul>\r\n\t<li>Total Schulgeld f\u00fcr den gesamten Lehrgang: 1365 CHF.<\/li>\r\n<\/ul>\r\n","format":"html","safe_value":"<ul><li>Total Schulgeld f\u00fcr den gesamten Lehrgang: 1365 CHF.<\/li>\n<\/ul>"}]},"field_master_nid":[],"field_study_variant":[],"field_visible_from":[],"rdf_mapping":{"rdftype":["sioc:Item","foaf:Document"],"title":{"predicates":["dc:title"]},"created":{"predicates":["dc:date","dc:created"],"datatype":"xsd:dateTime","callback":"date_iso8601"},"changed":{"predicates":["dc:modified"],"datatype":"xsd:dateTime","callback":"date_iso8601"},"body":{"predicates":["content:encoded"]},"uid":{"predicates":["sioc:has_creator"],"type":"rel"},"name":{"predicates":["foaf:name"]},"comment_count":{"predicates":["sioc:num_replies"],"datatype":"xsd:integer"},"last_activity":{"predicates":["sioc:last_activity_date"],"datatype":"xsd:dateTime","callback":"date_iso8601"}},"path":{"pathauto":"1"},"cid":"0","last_comment_timestamp":"1481297443","last_comment_name":null,"last_comment_uid":"19410","comment_count":"0","name":"Aranshi Abraham","picture":"0","data":"a:1:{s:17:\"mimemail_textonly\";i:0;}"},"16969":{"vid":"16970","uid":"19410","title":"   1-Spr-I-A1-Startdaten Vm6","log":"","status":"1","comment":"1","promote":"0","sticky":"0","ds_switch":"","nid":"16969","type":"course_times","language":"de","created":"1481297482","changed":"1481297482","tnid":"0","translate":"0","revision_timestamp":"1481297482","revision_uid":"19410","body":{"und":[{"value":"<p>Sa Vormittag<\/p>\r\n","summary":"","format":"html","safe_value":"<p>Sa Vormittag<\/p>\n","safe_summary":""}]},"field_course_date":{"und":[{"value":"2017-06-10 00:00:00","value2":"2018-02-03 00:00:00","timezone":"Europe\/Zurich","timezone_db":"Europe\/Zurich","date_type":"datetime"}]},"field_has_fsv":{"und":[{"value":"0"}]},"field_course":{"und":[{"target_id":"14951"}]},"field_location":{"und":[{"target_id":"6687"}]},"field_brutto_price":{"und":[{"value":"1365"}]},"field_netto_price":[],"field_anmeldungs_link":[],"field_template":{"und":[{"value":"default"}]},"field_detailed_price":{"und":[{"value":"<ul>\r\n\t<li>Total Schulgeld f\u00fcr den gesamten Lehrgang: 1365 CHF.<\/li>\r\n<\/ul>\r\n","format":"html","safe_value":"<ul><li>Total Schulgeld f\u00fcr den gesamten Lehrgang: 1365 CHF.<\/li>\n<\/ul>"}]},"field_master_nid":[],"field_study_variant":[],"field_visible_from":[],"rdf_mapping":{"rdftype":["sioc:Item","foaf:Document"],"title":{"predicates":["dc:title"]},"created":{"predicates":["dc:date","dc:created"],"datatype":"xsd:dateTime","callback":"date_iso8601"},"changed":{"predicates":["dc:modified"],"datatype":"xsd:dateTime","callback":"date_iso8601"},"body":{"predicates":["content:encoded"]},"uid":{"predicates":["sioc:has_creator"],"type":"rel"},"name":{"predicates":["foaf:name"]},"comment_count":{"predicates":["sioc:num_replies"],"datatype":"xsd:integer"},"last_activity":{"predicates":["sioc:last_activity_date"],"datatype":"xsd:dateTime","callback":"date_iso8601"}},"path":{"pathauto":"1"},"cid":"0","last_comment_timestamp":"1481297482","last_comment_name":null,"last_comment_uid":"19410","comment_count":"0","name":"Aranshi Abraham","picture":"0","data":"a:1:{s:17:\"mimemail_textonly\";i:0;}"},"17654":{"vid":"17655","uid":"19406","title":"1-Spr-I-A1-Startdaten Ab8","log":"","status":"1","comment":"1","promote":"0","sticky":"0","ds_switch":"","nid":"17654","type":"course_times","language":"de","created":"1497355247","changed":"1497871266","tnid":"0","translate":"0","revision_timestamp":"1497871266","revision_uid":"19406","body":{"und":[{"value":"<p>Mo Abend<br \/>\r\n25 Wo x 3 Lekt = 75 Lektionen<br \/>\r\nFr. 1'365.-- (+Lehrmittel: Fr. 80.--)<\/p>\r\n","summary":"","format":"html","safe_value":"<p>Mo Abend<br \/>\n25 Wo x 3 Lekt = 75 Lektionen<br \/>\nFr. 1'365.-- (+Lehrmittel: Fr. 80.--)<\/p>\n","safe_summary":""}]},"field_course_date":{"und":[{"value":"2017-08-21 00:00:00","value2":"2018-02-19 00:00:00","timezone":"Europe\/Zurich","timezone_db":"Europe\/Zurich","date_type":"datetime"}]},"field_has_fsv":{"und":[{"value":"0"}]},"field_course":{"und":[{"target_id":"14951"}]},"field_location":{"und":[{"target_id":"6687"}]},"field_brutto_price":{"und":[{"value":"1365"}]},"field_netto_price":[],"field_anmeldungs_link":[],"field_template":{"und":[{"value":"default"}]},"field_detailed_price":{"und":[{"value":"<ul>\r\n\t<li>Total Schulgeld f\u00fcr den gesamten Lehrgang: 1365 CHF.<\/li>\r\n<\/ul>\r\n","format":"html","safe_value":"<ul><li>Total Schulgeld f\u00fcr den gesamten Lehrgang: 1365 CHF.<\/li>\n<\/ul>"}]},"field_master_nid":[],"field_study_variant":[],"field_visible_from":[],"rdf_mapping":{"rdftype":["sioc:Item","foaf:Document"],"title":{"predicates":["dc:title"]},"created":{"predicates":["dc:date","dc:created"],"datatype":"xsd:dateTime","callback":"date_iso8601"},"changed":{"predicates":["dc:modified"],"datatype":"xsd:dateTime","callback":"date_iso8601"},"body":{"predicates":["content:encoded"]},"uid":{"predicates":["sioc:has_creator"],"type":"rel"},"name":{"predicates":["foaf:name"]},"comment_count":{"predicates":["sioc:num_replies"],"datatype":"xsd:integer"},"last_activity":{"predicates":["sioc:last_activity_date"],"datatype":"xsd:dateTime","callback":"date_iso8601"}},"path":{"pathauto":"1"},"cid":"0","last_comment_timestamp":"1497355247","last_comment_name":null,"last_comment_uid":"19406","comment_count":"0","name":"Frank Merola","picture":"0","data":"a:1:{s:17:\"mimemail_textonly\";i:0;}"},"17655":{"vid":"17656","uid":"19406","title":"1-Spr-I-A1-Startdaten SVm8","log":"","status":"1","comment":"1","promote":"0","sticky":"0","ds_switch":"","nid":"17655","type":"course_times","language":"de","created":"1497355339","changed":"1497881641","tnid":"0","translate":"0","revision_timestamp":"1497881641","revision_uid":"19406","body":{"und":[{"value":"<p>Sa Vormittag<br \/>\r\n25 Wo x 3 Lekt = 75 Lektionen<br \/>\r\nFr. 1'365.-- (+Lehrmittel: Fr. 80.--)<\/p>\r\n","summary":"","format":"html","safe_value":"<p>Sa Vormittag<br \/>\n25 Wo x 3 Lekt = 75 Lektionen<br \/>\nFr. 1'365.-- (+Lehrmittel: Fr. 80.--)<\/p>\n","safe_summary":""}]},"field_course_date":{"und":[{"value":"2017-08-19 00:00:00","value2":"2018-02-17 00:00:00","timezone":"Europe\/Zurich","timezone_db":"Europe\/Zurich","date_type":"datetime"}]},"field_has_fsv":{"und":[{"value":"0"}]},"field_course":{"und":[{"target_id":"14951"}]},"field_location":{"und":[{"target_id":"6687"}]},"field_brutto_price":{"und":[{"value":"1365"}]},"field_netto_price":[],"field_anmeldungs_link":[],"field_template":{"und":[{"value":"default"}]},"field_detailed_price":{"und":[{"value":"<ul>\r\n\t<li>Total Schulgeld f\u00fcr den gesamten Lehrgang: 1365 CHF.<\/li>\r\n<\/ul>\r\n","format":"html","safe_value":"<ul><li>Total Schulgeld f\u00fcr den gesamten Lehrgang: 1365 CHF.<\/li>\n<\/ul>"}]},"field_master_nid":[],"field_study_variant":[],"field_visible_from":[],"rdf_mapping":{"rdftype":["sioc:Item","foaf:Document"],"title":{"predicates":["dc:title"]},"created":{"predicates":["dc:date","dc:created"],"datatype":"xsd:dateTime","callback":"date_iso8601"},"changed":{"predicates":["dc:modified"],"datatype":"xsd:dateTime","callback":"date_iso8601"},"body":{"predicates":["content:encoded"]},"uid":{"predicates":["sioc:has_creator"],"type":"rel"},"name":{"predicates":["foaf:name"]},"comment_count":{"predicates":["sioc:num_replies"],"datatype":"xsd:integer"},"last_activity":{"predicates":["sioc:last_activity_date"],"datatype":"xsd:dateTime","callback":"date_iso8601"}},"path":{"pathauto":"1"},"cid":"0","last_comment_timestamp":"1497355339","last_comment_name":null,"last_comment_uid":"19406","comment_count":"0","name":"Frank Merola","picture":"0","data":"a:1:{s:17:\"mimemail_textonly\";i:0;}"},"17706":{"vid":"17707","uid":"19406","title":"1-Spr-I-A1-Startdaten Ab In8","log":"","status":"1","comment":"1","promote":"0","sticky":"0","ds_switch":"","nid":"17706","type":"course_times","language":"de","created":"1497447806","changed":"1497447806","tnid":"0","translate":"0","revision_timestamp":"1497447806","revision_uid":"19406","body":{"und":[{"value":"<p>Mo &amp; Mi Abend- Intensiv<br \/>\r\n12.5 Wo x 6 Lekt = 75 Lektionen<br \/>\r\nFr. 1'365.-- (+Lehrmittel: Fr. 80.--)<\/p>\r\n","summary":"","format":"html","safe_value":"<p>Mo &amp; Mi Abend- Intensiv<br \/>\n12.5 Wo x 6 Lekt = 75 Lektionen<br \/>\nFr. 1'365.-- (+Lehrmittel: Fr. 80.--)<\/p>\n","safe_summary":""}]},"field_course_date":{"und":[{"value":"2017-08-21 00:00:00","value2":"2017-11-27 00:00:00","timezone":"Europe\/Zurich","timezone_db":"Europe\/Zurich","date_type":"datetime"}]},"field_has_fsv":{"und":[{"value":"0"}]},"field_course":{"und":[{"target_id":"14951"}]},"field_location":{"und":[{"target_id":"6687"}]},"field_brutto_price":{"und":[{"value":"1365"}]},"field_netto_price":[],"field_anmeldungs_link":[],"field_template":{"und":[{"value":"default"}]},"field_detailed_price":{"und":[{"value":"<ul>\r\n\t<li>Total Schulgeld f\u00fcr den gesamten Lehrgang: 1365 CHF.<\/li>\r\n<\/ul>\r\n","format":"html","safe_value":"<ul><li>Total Schulgeld f\u00fcr den gesamten Lehrgang: 1365 CHF.<\/li>\n<\/ul>"}]},"field_master_nid":[],"field_study_variant":[],"field_visible_from":[],"rdf_mapping":{"rdftype":["sioc:Item","foaf:Document"],"title":{"predicates":["dc:title"]},"created":{"predicates":["dc:date","dc:created"],"datatype":"xsd:dateTime","callback":"date_iso8601"},"changed":{"predicates":["dc:modified"],"datatype":"xsd:dateTime","callback":"date_iso8601"},"body":{"predicates":["content:encoded"]},"uid":{"predicates":["sioc:has_creator"],"type":"rel"},"name":{"predicates":["foaf:name"]},"comment_count":{"predicates":["sioc:num_replies"],"datatype":"xsd:integer"},"last_activity":{"predicates":["sioc:last_activity_date"],"datatype":"xsd:dateTime","callback":"date_iso8601"}},"path":{"pathauto":"1"},"cid":"0","last_comment_timestamp":"1497447806","last_comment_name":null,"last_comment_uid":"19406","comment_count":"0","name":"Frank Merola","picture":"0","data":"a:1:{s:17:\"mimemail_textonly\";i:0;}"},"17851":{"vid":"17852","uid":"19406","title":"1-Spr-I-A1-Startdaten Ab9","log":"","status":"1","comment":"1","promote":"0","sticky":"0","ds_switch":"","nid":"17851","type":"course_times","language":"de","created":"1498051687","changed":"1498051727","tnid":"0","translate":"0","revision_timestamp":"1498051727","revision_uid":"19406","body":{"und":[{"value":"<p>Mo Abend<br \/>\r\n25 Wo x 3 Lekt = 75 Lektionen<br \/>\r\nFr. 1'365.-- (+Lehrmittel: Fr. 80.--)<\/p>\r\n","summary":"","format":"html","safe_value":"<p>Mo Abend<br \/>\n25 Wo x 3 Lekt = 75 Lektionen<br \/>\nFr. 1'365.-- (+Lehrmittel: Fr. 80.--)<\/p>\n","safe_summary":""}]},"field_course_date":{"und":[{"value":"2017-09-18 00:00:00","value2":"2018-03-19 00:00:00","timezone":"Europe\/Zurich","timezone_db":"Europe\/Zurich","date_type":"datetime"}]},"field_has_fsv":{"und":[{"value":"0"}]},"field_course":{"und":[{"target_id":"14951"}]},"field_location":{"und":[{"target_id":"6687"}]},"field_brutto_price":{"und":[{"value":"1365"}]},"field_netto_price":[],"field_anmeldungs_link":[],"field_template":{"und":[{"value":"default"}]},"field_detailed_price":{"und":[{"value":"<ul>\r\n\t<li>Total Schulgeld f\u00fcr den gesamten Lehrgang: 1365 CHF.<\/li>\r\n<\/ul>\r\n","format":"html","safe_value":"<ul><li>Total Schulgeld f\u00fcr den gesamten Lehrgang: 1365 CHF.<\/li>\n<\/ul>"}]},"field_master_nid":[],"field_study_variant":[],"field_visible_from":[],"rdf_mapping":{"rdftype":["sioc:Item","foaf:Document"],"title":{"predicates":["dc:title"]},"created":{"predicates":["dc:date","dc:created"],"datatype":"xsd:dateTime","callback":"date_iso8601"},"changed":{"predicates":["dc:modified"],"datatype":"xsd:dateTime","callback":"date_iso8601"},"body":{"predicates":["content:encoded"]},"uid":{"predicates":["sioc:has_creator"],"type":"rel"},"name":{"predicates":["foaf:name"]},"comment_count":{"predicates":["sioc:num_replies"],"datatype":"xsd:integer"},"last_activity":{"predicates":["sioc:last_activity_date"],"datatype":"xsd:dateTime","callback":"date_iso8601"}},"path":{"pathauto":"1"},"cid":"0","last_comment_timestamp":"1498051687","last_comment_name":null,"last_comment_uid":"19406","comment_count":"0","name":"Frank Merola","picture":"0","data":"a:1:{s:17:\"mimemail_textonly\";i:0;}"},"17852":{"vid":"17853","uid":"19406","title":"1-Spr-I-A1-Startdaten Ab In9","log":"","status":"1","comment":"1","promote":"0","sticky":"0","ds_switch":"","nid":"17852","type":"course_times","language":"de","created":"1498051768","changed":"1498132622","tnid":"0","translate":"0","revision_timestamp":"1498132622","revision_uid":"19406","body":{"und":[{"value":"<p>Mo &amp; Mi Abend- Intensiv<br \/>\r\n12.5 Wo x 6 Lekt = 75 Lektionen<br \/>\r\nFr. 1'365.-- (+Lehrmittel: Fr. 80.--)<\/p>\r\n","summary":"","format":"html","safe_value":"<p>Mo &amp; Mi Abend- Intensiv<br \/>\n12.5 Wo x 6 Lekt = 75 Lektionen<br \/>\nFr. 1'365.-- (+Lehrmittel: Fr. 80.--)<\/p>\n","safe_summary":""}]},"field_course_date":{"und":[{"value":"2017-09-18 00:00:00","value2":"2017-12-18 00:00:00","timezone":"Europe\/Zurich","timezone_db":"Europe\/Zurich","date_type":"datetime"}]},"field_has_fsv":{"und":[{"value":"0"}]},"field_course":{"und":[{"target_id":"14951"}]},"field_location":{"und":[{"target_id":"6687"}]},"field_brutto_price":{"und":[{"value":"1365"}]},"field_netto_price":[],"field_anmeldungs_link":[],"field_template":{"und":[{"value":"default"}]},"field_detailed_price":{"und":[{"value":"<ul>\r\n\t<li>Total Schulgeld f\u00fcr den gesamten Lehrgang: 1365 CHF.<\/li>\r\n<\/ul>\r\n","format":"html","safe_value":"<ul><li>Total Schulgeld f\u00fcr den gesamten Lehrgang: 1365 CHF.<\/li>\n<\/ul>"}]},"field_master_nid":[],"field_study_variant":[],"field_visible_from":[],"rdf_mapping":{"rdftype":["sioc:Item","foaf:Document"],"title":{"predicates":["dc:title"]},"created":{"predicates":["dc:date","dc:created"],"datatype":"xsd:dateTime","callback":"date_iso8601"},"changed":{"predicates":["dc:modified"],"datatype":"xsd:dateTime","callback":"date_iso8601"},"body":{"predicates":["content:encoded"]},"uid":{"predicates":["sioc:has_creator"],"type":"rel"},"name":{"predicates":["foaf:name"]},"comment_count":{"predicates":["sioc:num_replies"],"datatype":"xsd:integer"},"last_activity":{"predicates":["sioc:last_activity_date"],"datatype":"xsd:dateTime","callback":"date_iso8601"}},"path":{"pathauto":"1"},"cid":"0","last_comment_timestamp":"1498051768","last_comment_name":null,"last_comment_uid":"19406","comment_count":"0","name":"Frank Merola","picture":"0","data":"a:1:{s:17:\"mimemail_textonly\";i:0;}"},"17853":{"vid":"17854","uid":"19406","title":"1-Spr-I-A1-Startdaten SVm9","log":"","status":"1","comment":"1","promote":"0","sticky":"0","ds_switch":"","nid":"17853","type":"course_times","language":"de","created":"1498051817","changed":"1498051817","tnid":"0","translate":"0","revision_timestamp":"1498051817","revision_uid":"19406","body":{"und":[{"value":"<p>Sa Vormittag<br \/>\r\n25 Wo x 3 Lekt = 75 Lektionen<br \/>\r\nFr. 1'365.-- (+Lehrmittel: Fr. 80.--)<\/p>\r\n","summary":"","format":"html","safe_value":"<p>Sa Vormittag<br \/>\n25 Wo x 3 Lekt = 75 Lektionen<br \/>\nFr. 1'365.-- (+Lehrmittel: Fr. 80.--)<\/p>\n","safe_summary":""}]},"field_course_date":{"und":[{"value":"2017-09-23 00:00:00","value2":"2018-03-24 00:00:00","timezone":"Europe\/Zurich","timezone_db":"Europe\/Zurich","date_type":"datetime"}]},"field_has_fsv":{"und":[{"value":"0"}]},"field_course":{"und":[{"target_id":"14951"}]},"field_location":{"und":[{"target_id":"6687"}]},"field_brutto_price":{"und":[{"value":"1365"}]},"field_netto_price":[],"field_anmeldungs_link":[],"field_template":{"und":[{"value":"default"}]},"field_detailed_price":{"und":[{"value":"<ul>\r\n\t<li>Total Schulgeld f\u00fcr den gesamten Lehrgang: 1365 CHF.<\/li>\r\n<\/ul>\r\n","format":"html","safe_value":"<ul><li>Total Schulgeld f\u00fcr den gesamten Lehrgang: 1365 CHF.<\/li>\n<\/ul>"}]},"field_master_nid":[],"field_study_variant":[],"field_visible_from":[],"rdf_mapping":{"rdftype":["sioc:Item","foaf:Document"],"title":{"predicates":["dc:title"]},"created":{"predicates":["dc:date","dc:created"],"datatype":"xsd:dateTime","callback":"date_iso8601"},"changed":{"predicates":["dc:modified"],"datatype":"xsd:dateTime","callback":"date_iso8601"},"body":{"predicates":["content:encoded"]},"uid":{"predicates":["sioc:has_creator"],"type":"rel"},"name":{"predicates":["foaf:name"]},"comment_count":{"predicates":["sioc:num_replies"],"datatype":"xsd:integer"},"last_activity":{"predicates":["sioc:last_activity_date"],"datatype":"xsd:dateTime","callback":"date_iso8601"}},"path":{"pathauto":"1"},"cid":"0","last_comment_timestamp":"1498051817","last_comment_name":null,"last_comment_uid":"19406","comment_count":"0","name":"Frank Merola","picture":"0","data":"a:1:{s:17:\"mimemail_textonly\";i:0;}"},"18414":{"vid":"18415","uid":"19406","title":"1-Spr-I-A1-Startdaten Ab10","log":"","status":"1","comment":"1","promote":"0","sticky":"0","ds_switch":"","nid":"18414","type":"course_times","language":"de","created":"1505474271","changed":"1505474271","tnid":"0","translate":"0","revision_timestamp":"1505474271","revision_uid":"19406","body":{"und":[{"value":"<p>Mo Abend<br \/>\r\n25 Wo x 3 Lekt = 75 Lektionen<br \/>\r\nFr. 1'365.-- (+Lehrmittel: Fr. 80.--)<\/p>\r\n","summary":"","format":"html","safe_value":"<p>Mo Abend<br \/>\n25 Wo x 3 Lekt = 75 Lektionen<br \/>\nFr. 1'365.-- (+Lehrmittel: Fr. 80.--)<\/p>\n","safe_summary":""}]},"field_course_date":{"und":[{"value":"2017-10-16 00:00:00","value2":"2018-04-16 00:00:00","timezone":"Europe\/Zurich","timezone_db":"Europe\/Zurich","date_type":"datetime"}]},"field_has_fsv":{"und":[{"value":"0"}]},"field_course":{"und":[{"target_id":"14951"}]},"field_location":{"und":[{"target_id":"6687"}]},"field_brutto_price":{"und":[{"value":"1365"}]},"field_netto_price":[],"field_anmeldungs_link":[],"field_template":{"und":[{"value":"default"}]},"field_detailed_price":{"und":[{"value":"<ul>\r\n\t<li>Total Schulgeld f\u00fcr den gesamten Lehrgang: 1365 CHF.<\/li>\r\n<\/ul>\r\n","format":"html","safe_value":"<ul><li>Total Schulgeld f\u00fcr den gesamten Lehrgang: 1365 CHF.<\/li>\n<\/ul>"}]},"field_master_nid":[],"field_study_variant":[],"field_visible_from":{"und":[{"value":"2017-09-15 13:15:00","timezone":"Europe\/Zurich","timezone_db":"Europe\/Zurich","date_type":"datetime"}]},"rdf_mapping":{"rdftype":["sioc:Item","foaf:Document"],"title":{"predicates":["dc:title"]},"created":{"predicates":["dc:date","dc:created"],"datatype":"xsd:dateTime","callback":"date_iso8601"},"changed":{"predicates":["dc:modified"],"datatype":"xsd:dateTime","callback":"date_iso8601"},"body":{"predicates":["content:encoded"]},"uid":{"predicates":["sioc:has_creator"],"type":"rel"},"name":{"predicates":["foaf:name"]},"comment_count":{"predicates":["sioc:num_replies"],"datatype":"xsd:integer"},"last_activity":{"predicates":["sioc:last_activity_date"],"datatype":"xsd:dateTime","callback":"date_iso8601"}},"path":{"pathauto":"1"},"cid":"0","last_comment_timestamp":"1505474271","last_comment_name":null,"last_comment_uid":"19406","comment_count":"0","name":"Frank Merola","picture":"0","data":"a:1:{s:17:\"mimemail_textonly\";i:0;}"},"18415":{"vid":"18416","uid":"19406","title":"1-Spr-I-A1-Startdaten Ab11","log":"","status":"1","comment":"1","promote":"0","sticky":"0","ds_switch":"","nid":"18415","type":"course_times","language":"de","created":"1505474294","changed":"1505474294","tnid":"0","translate":"0","revision_timestamp":"1505474294","revision_uid":"19406","body":{"und":[{"value":"<p>Mo Abend<br \/>\r\n25 Wo x 3 Lekt = 75 Lektionen<br \/>\r\nFr. 1'365.-- (+Lehrmittel: Fr. 80.--)<\/p>\r\n","summary":"","format":"html","safe_value":"<p>Mo Abend<br \/>\n25 Wo x 3 Lekt = 75 Lektionen<br \/>\nFr. 1'365.-- (+Lehrmittel: Fr. 80.--)<\/p>\n","safe_summary":""}]},"field_course_date":{"und":[{"value":"2017-11-13 00:00:00","value2":"2018-05-14 00:00:00","timezone":"Europe\/Zurich","timezone_db":"Europe\/Zurich","date_type":"datetime"}]},"field_has_fsv":{"und":[{"value":"0"}]},"field_course":{"und":[{"target_id":"14951"}]},"field_location":{"und":[{"target_id":"6687"}]},"field_brutto_price":{"und":[{"value":"1365"}]},"field_netto_price":[],"field_anmeldungs_link":[],"field_template":{"und":[{"value":"default"}]},"field_detailed_price":{"und":[{"value":"<ul>\r\n\t<li>Total Schulgeld f\u00fcr den gesamten Lehrgang: 1365 CHF.<\/li>\r\n<\/ul>\r\n","format":"html","safe_value":"<ul><li>Total Schulgeld f\u00fcr den gesamten Lehrgang: 1365 CHF.<\/li>\n<\/ul>"}]},"field_master_nid":[],"field_study_variant":[],"field_visible_from":{"und":[{"value":"2017-09-15 13:15:00","timezone":"Europe\/Zurich","timezone_db":"Europe\/Zurich","date_type":"datetime"}]},"rdf_mapping":{"rdftype":["sioc:Item","foaf:Document"],"title":{"predicates":["dc:title"]},"created":{"predicates":["dc:date","dc:created"],"datatype":"xsd:dateTime","callback":"date_iso8601"},"changed":{"predicates":["dc:modified"],"datatype":"xsd:dateTime","callback":"date_iso8601"},"body":{"predicates":["content:encoded"]},"uid":{"predicates":["sioc:has_creator"],"type":"rel"},"name":{"predicates":["foaf:name"]},"comment_count":{"predicates":["sioc:num_replies"],"datatype":"xsd:integer"},"last_activity":{"predicates":["sioc:last_activity_date"],"datatype":"xsd:dateTime","callback":"date_iso8601"}},"path":{"pathauto":"1"},"cid":"0","last_comment_timestamp":"1505474294","last_comment_name":null,"last_comment_uid":"19406","comment_count":"0","name":"Frank Merola","picture":"0","data":"a:1:{s:17:\"mimemail_textonly\";i:0;}"},"18416":{"vid":"18417","uid":"19406","title":"1-Spr-I-A1-Startdaten Ab In10","log":"","status":"1","comment":"1","promote":"0","sticky":"0","ds_switch":"","nid":"18416","type":"course_times","language":"de","created":"1505474362","changed":"1505474362","tnid":"0","translate":"0","revision_timestamp":"1505474362","revision_uid":"19406","body":{"und":[{"value":"<p>Mo &amp; Mi Abend- Intensiv<br \/>\r\n12.5 Wo x 6 Lekt = 75 Lektionen<br \/>\r\nFr. 1'365.-- (+Lehrmittel: Fr. 80.--)<\/p>\r\n","summary":"","format":"html","safe_value":"<p>Mo &amp; Mi Abend- Intensiv<br \/>\n12.5 Wo x 6 Lekt = 75 Lektionen<br \/>\nFr. 1'365.-- (+Lehrmittel: Fr. 80.--)<\/p>\n","safe_summary":""}]},"field_course_date":{"und":[{"value":"2017-10-16 00:00:00","value2":"2018-01-22 00:00:00","timezone":"Europe\/Zurich","timezone_db":"Europe\/Zurich","date_type":"datetime"}]},"field_has_fsv":{"und":[{"value":"0"}]},"field_course":{"und":[{"target_id":"14951"}]},"field_location":{"und":[{"target_id":"6687"}]},"field_brutto_price":{"und":[{"value":"1365"}]},"field_netto_price":[],"field_anmeldungs_link":[],"field_template":{"und":[{"value":"default"}]},"field_detailed_price":{"und":[{"value":"<ul>\r\n\t<li>Total Schulgeld f\u00fcr den gesamten Lehrgang: 1365 CHF.<\/li>\r\n<\/ul>\r\n","format":"html","safe_value":"<ul><li>Total Schulgeld f\u00fcr den gesamten Lehrgang: 1365 CHF.<\/li>\n<\/ul>"}]},"field_master_nid":[],"field_study_variant":[],"field_visible_from":{"und":[{"value":"2017-09-15 13:15:00","timezone":"Europe\/Zurich","timezone_db":"Europe\/Zurich","date_type":"datetime"}]},"rdf_mapping":{"rdftype":["sioc:Item","foaf:Document"],"title":{"predicates":["dc:title"]},"created":{"predicates":["dc:date","dc:created"],"datatype":"xsd:dateTime","callback":"date_iso8601"},"changed":{"predicates":["dc:modified"],"datatype":"xsd:dateTime","callback":"date_iso8601"},"body":{"predicates":["content:encoded"]},"uid":{"predicates":["sioc:has_creator"],"type":"rel"},"name":{"predicates":["foaf:name"]},"comment_count":{"predicates":["sioc:num_replies"],"datatype":"xsd:integer"},"last_activity":{"predicates":["sioc:last_activity_date"],"datatype":"xsd:dateTime","callback":"date_iso8601"}},"path":{"pathauto":"1"},"cid":"0","last_comment_timestamp":"1505474362","last_comment_name":null,"last_comment_uid":"19406","comment_count":"0","name":"Frank Merola","picture":"0","data":"a:1:{s:17:\"mimemail_textonly\";i:0;}"},"18417":{"vid":"18418","uid":"19406","title":"1-Spr-I-A1-Startdaten Ab In11","log":"","status":"1","comment":"1","promote":"0","sticky":"0","ds_switch":"","nid":"18417","type":"course_times","language":"de","created":"1505474405","changed":"1505474405","tnid":"0","translate":"0","revision_timestamp":"1505474405","revision_uid":"19406","body":{"und":[{"value":"<p>Mo &amp; Mi Abend- Intensiv<br \/>\r\n12.5 Wo x 6 Lekt = 75 Lektionen<br \/>\r\nFr. 1'365.-- (+Lehrmittel: Fr. 80.--)<\/p>\r\n","summary":"","format":"html","safe_value":"<p>Mo &amp; Mi Abend- Intensiv<br \/>\n12.5 Wo x 6 Lekt = 75 Lektionen<br \/>\nFr. 1'365.-- (+Lehrmittel: Fr. 80.--)<\/p>\n","safe_summary":""}]},"field_course_date":{"und":[{"value":"2017-11-13 00:00:00","value2":"2018-02-19 00:00:00","timezone":"Europe\/Zurich","timezone_db":"Europe\/Zurich","date_type":"datetime"}]},"field_has_fsv":{"und":[{"value":"0"}]},"field_course":{"und":[{"target_id":"14951"}]},"field_location":{"und":[{"target_id":"6687"}]},"field_brutto_price":{"und":[{"value":"1365"}]},"field_netto_price":[],"field_anmeldungs_link":[],"field_template":{"und":[{"value":"default"}]},"field_detailed_price":{"und":[{"value":"<ul>\r\n\t<li>Total Schulgeld f\u00fcr den gesamten Lehrgang: 1365 CHF.<\/li>\r\n<\/ul>\r\n","format":"html","safe_value":"<ul><li>Total Schulgeld f\u00fcr den gesamten Lehrgang: 1365 CHF.<\/li>\n<\/ul>"}]},"field_master_nid":[],"field_study_variant":[],"field_visible_from":{"und":[{"value":"2017-09-15 13:15:00","timezone":"Europe\/Zurich","timezone_db":"Europe\/Zurich","date_type":"datetime"}]},"rdf_mapping":{"rdftype":["sioc:Item","foaf:Document"],"title":{"predicates":["dc:title"]},"created":{"predicates":["dc:date","dc:created"],"datatype":"xsd:dateTime","callback":"date_iso8601"},"changed":{"predicates":["dc:modified"],"datatype":"xsd:dateTime","callback":"date_iso8601"},"body":{"predicates":["content:encoded"]},"uid":{"predicates":["sioc:has_creator"],"type":"rel"},"name":{"predicates":["foaf:name"]},"comment_count":{"predicates":["sioc:num_replies"],"datatype":"xsd:integer"},"last_activity":{"predicates":["sioc:last_activity_date"],"datatype":"xsd:dateTime","callback":"date_iso8601"}},"path":{"pathauto":"1"},"cid":"0","last_comment_timestamp":"1505474405","last_comment_name":null,"last_comment_uid":"19406","comment_count":"0","name":"Frank Merola","picture":"0","data":"a:1:{s:17:\"mimemail_textonly\";i:0;}"},"18419":{"vid":"18420","uid":"19406","title":"1-Spr-I-A1-Startdaten SVm10","log":"","status":"1","comment":"1","promote":"0","sticky":"0","ds_switch":"","nid":"18419","type":"course_times","language":"de","created":"1505474448","changed":"1505474448","tnid":"0","translate":"0","revision_timestamp":"1505474448","revision_uid":"19406","body":{"und":[{"value":"<p>Sa Vormittag<br \/>\r\n25 Wo x 3 Lekt = 75 Lektionen<br \/>\r\nFr. 1'365.-- (+Lehrmittel: Fr. 80.--)<\/p>\r\n","summary":"","format":"html","safe_value":"<p>Sa Vormittag<br \/>\n25 Wo x 3 Lekt = 75 Lektionen<br \/>\nFr. 1'365.-- (+Lehrmittel: Fr. 80.--)<\/p>\n","safe_summary":""}]},"field_course_date":{"und":[{"value":"2017-10-14 00:00:00","value2":"2018-04-14 00:00:00","timezone":"Europe\/Zurich","timezone_db":"Europe\/Zurich","date_type":"datetime"}]},"field_has_fsv":{"und":[{"value":"0"}]},"field_course":{"und":[{"target_id":"14951"}]},"field_location":{"und":[{"target_id":"6687"}]},"field_brutto_price":{"und":[{"value":"1365"}]},"field_netto_price":[],"field_anmeldungs_link":[],"field_template":{"und":[{"value":"default"}]},"field_detailed_price":{"und":[{"value":"<ul>\r\n\t<li>Total Schulgeld f\u00fcr den gesamten Lehrgang: 1365 CHF.<\/li>\r\n<\/ul>\r\n","format":"html","safe_value":"<ul><li>Total Schulgeld f\u00fcr den gesamten Lehrgang: 1365 CHF.<\/li>\n<\/ul>"}]},"field_master_nid":[],"field_study_variant":[],"field_visible_from":{"und":[{"value":"2017-09-15 13:15:00","timezone":"Europe\/Zurich","timezone_db":"Europe\/Zurich","date_type":"datetime"}]},"rdf_mapping":{"rdftype":["sioc:Item","foaf:Document"],"title":{"predicates":["dc:title"]},"created":{"predicates":["dc:date","dc:created"],"datatype":"xsd:dateTime","callback":"date_iso8601"},"changed":{"predicates":["dc:modified"],"datatype":"xsd:dateTime","callback":"date_iso8601"},"body":{"predicates":["content:encoded"]},"uid":{"predicates":["sioc:has_creator"],"type":"rel"},"name":{"predicates":["foaf:name"]},"comment_count":{"predicates":["sioc:num_replies"],"datatype":"xsd:integer"},"last_activity":{"predicates":["sioc:last_activity_date"],"datatype":"xsd:dateTime","callback":"date_iso8601"}},"path":{"pathauto":"1"},"cid":"0","last_comment_timestamp":"1505474448","last_comment_name":null,"last_comment_uid":"19406","comment_count":"0","name":"Frank Merola","picture":"0","data":"a:1:{s:17:\"mimemail_textonly\";i:0;}"},"18420":{"vid":"18421","uid":"19406","title":"1-Spr-I-A1-Startdaten SVm11","log":"","status":"1","comment":"1","promote":"0","sticky":"0","ds_switch":"","nid":"18420","type":"course_times","language":"de","created":"1505474470","changed":"1505474470","tnid":"0","translate":"0","revision_timestamp":"1505474470","revision_uid":"19406","body":{"und":[{"value":"<p>Sa Vormittag<br \/>\r\n25 Wo x 3 Lekt = 75 Lektionen<br \/>\r\nFr. 1'365.-- (+Lehrmittel: Fr. 80.--)<\/p>\r\n","summary":"","format":"html","safe_value":"<p>Sa Vormittag<br \/>\n25 Wo x 3 Lekt = 75 Lektionen<br \/>\nFr. 1'365.-- (+Lehrmittel: Fr. 80.--)<\/p>\n","safe_summary":""}]},"field_course_date":{"und":[{"value":"2017-11-11 00:00:00","value2":"2018-05-12 00:00:00","timezone":"Europe\/Zurich","timezone_db":"Europe\/Zurich","date_type":"datetime"}]},"field_has_fsv":{"und":[{"value":"0"}]},"field_course":{"und":[{"target_id":"14951"}]},"field_location":{"und":[{"target_id":"6687"}]},"field_brutto_price":{"und":[{"value":"1365"}]},"field_netto_price":[],"field_anmeldungs_link":[],"field_template":{"und":[{"value":"default"}]},"field_detailed_price":{"und":[{"value":"<ul>\r\n\t<li>Total Schulgeld f\u00fcr den gesamten Lehrgang: 1365 CHF.<\/li>\r\n<\/ul>\r\n","format":"html","safe_value":"<ul><li>Total Schulgeld f\u00fcr den gesamten Lehrgang: 1365 CHF.<\/li>\n<\/ul>"}]},"field_master_nid":[],"field_study_variant":[],"field_visible_from":{"und":[{"value":"2017-09-15 13:15:00","timezone":"Europe\/Zurich","timezone_db":"Europe\/Zurich","date_type":"datetime"}]},"rdf_mapping":{"rdftype":["sioc:Item","foaf:Document"],"title":{"predicates":["dc:title"]},"created":{"predicates":["dc:date","dc:created"],"datatype":"xsd:dateTime","callback":"date_iso8601"},"changed":{"predicates":["dc:modified"],"datatype":"xsd:dateTime","callback":"date_iso8601"},"body":{"predicates":["content:encoded"]},"uid":{"predicates":["sioc:has_creator"],"type":"rel"},"name":{"predicates":["foaf:name"]},"comment_count":{"predicates":["sioc:num_replies"],"datatype":"xsd:integer"},"last_activity":{"predicates":["sioc:last_activity_date"],"datatype":"xsd:dateTime","callback":"date_iso8601"}},"path":{"pathauto":"1"},"cid":"0","last_comment_timestamp":"1505474470","last_comment_name":null,"last_comment_uid":"19406","comment_count":"0","name":"Frank Merola","picture":"0","data":"a:1:{s:17:\"mimemail_textonly\";i:0;}"}},"course_tabs":{"15247":{"vid":"15248","uid":"19331","title":"2-Spr-I-A1-Programm","log":"","status":"1","comment":"1","promote":"0","sticky":"0","ds_switch":"","nid":"15247","type":"course_tabs","language":"de","created":"1475244596","changed":"1475244596","tnid":"0","translate":"0","revision_timestamp":"1475244596","revision_uid":"19331","body":{"und":[{"value":"<p>In diesem Kurs wird der Wortschatz stark erweitert&nbsp; und die Satzstrukturen werden verfeinert, so dass eine Verst\u00e4ndigung schon recht gut m\u00f6glich ist. Nach dem Besuch des Kurses kann die internationale Italienisch-Pr\u00fcfung \"TELC Italiano A1\" absolviert werden. Im Kurs erfolgt ein entsprechendes Pr\u00fcfungstraining.<\/p>\r\n","summary":"","format":"html","safe_value":"<p>In diesem Kurs wird der Wortschatz stark erweitert\u00a0 und die Satzstrukturen werden verfeinert, so dass eine Verst\u00e4ndigung schon recht gut m\u00f6glich ist. Nach dem Besuch des Kurses kann die internationale Italienisch-Pr\u00fcfung \"TELC Italiano A1\" absolviert werden. Im Kurs erfolgt ein entsprechendes Pr\u00fcfungstraining.<\/p>\n","safe_summary":""}]},"field_course":{"und":[{"target_id":"14951"}]},"field_tab_title":{"und":[{"value":"Programm","format":null,"safe_value":"Programm"}]},"rdf_mapping":{"rdftype":["sioc:Item","foaf:Document"],"title":{"predicates":["dc:title"]},"created":{"predicates":["dc:date","dc:created"],"datatype":"xsd:dateTime","callback":"date_iso8601"},"changed":{"predicates":["dc:modified"],"datatype":"xsd:dateTime","callback":"date_iso8601"},"body":{"predicates":["content:encoded"]},"uid":{"predicates":["sioc:has_creator"],"type":"rel"},"name":{"predicates":["foaf:name"]},"comment_count":{"predicates":["sioc:num_replies"],"datatype":"xsd:integer"},"last_activity":{"predicates":["sioc:last_activity_date"],"datatype":"xsd:dateTime","callback":"date_iso8601"}},"path":{"pathauto":"1"},"cid":"0","last_comment_timestamp":"1475244596","last_comment_name":null,"last_comment_uid":"19331","comment_count":"0","name":"Thomas Schiendorfer","picture":"0","data":"a:2:{s:17:\"mimemail_textonly\";i:0;s:7:\"overlay\";i:1;}"},"15248":{"vid":"15249","uid":"19331","title":"3-Spr-I-A1-Teilnehmer","log":"","status":"1","comment":"1","promote":"0","sticky":"0","ds_switch":"","nid":"15248","type":"course_tabs","language":"de","created":"1475244654","changed":"1478248359","tnid":"0","translate":"0","revision_timestamp":"1478248359","revision_uid":"19331","body":{"und":[{"value":"<p>Personen, die auf Anf\u00e4ngerstufe ihr Italienisch weiterentwicklen wollen und evtl. ein A1-Sprachdiplom erlangen m\u00f6chten. Grundkenntnisse werden vorausgesetzt.<\/p>\r\n","summary":"","format":"html","safe_value":"<p>Personen, die auf Anf\u00e4ngerstufe ihr Italienisch weiterentwicklen wollen und evtl. ein A1-Sprachdiplom erlangen m\u00f6chten. Grundkenntnisse werden vorausgesetzt.<\/p>\n","safe_summary":""}]},"field_course":{"und":[{"target_id":"14951"}]},"field_tab_title":{"und":[{"value":"Teilnehmer","format":null,"safe_value":"Teilnehmer"}]},"rdf_mapping":{"rdftype":["sioc:Item","foaf:Document"],"title":{"predicates":["dc:title"]},"created":{"predicates":["dc:date","dc:created"],"datatype":"xsd:dateTime","callback":"date_iso8601"},"changed":{"predicates":["dc:modified"],"datatype":"xsd:dateTime","callback":"date_iso8601"},"body":{"predicates":["content:encoded"]},"uid":{"predicates":["sioc:has_creator"],"type":"rel"},"name":{"predicates":["foaf:name"]},"comment_count":{"predicates":["sioc:num_replies"],"datatype":"xsd:integer"},"last_activity":{"predicates":["sioc:last_activity_date"],"datatype":"xsd:dateTime","callback":"date_iso8601"}},"path":{"pathauto":"1"},"cid":"0","last_comment_timestamp":"1475244654","last_comment_name":null,"last_comment_uid":"19331","comment_count":"0","name":"Thomas Schiendorfer","picture":"0","data":"a:2:{s:17:\"mimemail_textonly\";i:0;s:7:\"overlay\";i:1;}"},"15249":{"vid":"15250","uid":"19331","title":"4-Spr-I-A1-System","log":"","status":"1","comment":"1","promote":"0","sticky":"0","ds_switch":"","nid":"15249","type":"course_tabs","language":"de","created":"1475244707","changed":"1475244707","tnid":"0","translate":"0","revision_timestamp":"1475244707","revision_uid":"19331","body":{"und":[{"value":"<p>Unsere Italienischkurse sind bestm\u00f6glich auf die Kompetenzstufen des Gemeinsamen Europ\u00e4ischen Referenzrahmens GER (Stufen A1, A2, B1, B2, C1, C2) ausgerichtet. Ab Stufe A1 bereiten sie auf anerkannte Diplome vor, insbesondere die bekannten CELI-Diplome sowie die TELC-Diplome. Unterrichtet wird mit bew\u00e4hrten Lehrmitteln, durch fachkundige Lehrkr\u00e4fte und ausschliesslich in kleinen Gruppen. Die Teilnehmerzahl betr\u00e4gt 4-7 Lernende (Standardkurse) bzw. 2-5 Lernende (Konversations- und Reisekurse).<\/p>\r\n","summary":"","format":"html","safe_value":"<p>Unsere Italienischkurse sind bestm\u00f6glich auf die Kompetenzstufen des Gemeinsamen Europ\u00e4ischen Referenzrahmens GER (Stufen A1, A2, B1, B2, C1, C2) ausgerichtet. Ab Stufe A1 bereiten sie auf anerkannte Diplome vor, insbesondere die bekannten CELI-Diplome sowie die TELC-Diplome. Unterrichtet wird mit bew\u00e4hrten Lehrmitteln, durch fachkundige Lehrkr\u00e4fte und ausschliesslich in kleinen Gruppen. Die Teilnehmerzahl betr\u00e4gt 4-7 Lernende (Standardkurse) bzw. 2-5 Lernende (Konversations- und Reisekurse).<\/p>\n","safe_summary":""}]},"field_course":{"und":[{"target_id":"14951"}]},"field_tab_title":{"und":[{"value":"System","format":null,"safe_value":"System"}]},"rdf_mapping":{"rdftype":["sioc:Item","foaf:Document"],"title":{"predicates":["dc:title"]},"created":{"predicates":["dc:date","dc:created"],"datatype":"xsd:dateTime","callback":"date_iso8601"},"changed":{"predicates":["dc:modified"],"datatype":"xsd:dateTime","callback":"date_iso8601"},"body":{"predicates":["content:encoded"]},"uid":{"predicates":["sioc:has_creator"],"type":"rel"},"name":{"predicates":["foaf:name"]},"comment_count":{"predicates":["sioc:num_replies"],"datatype":"xsd:integer"},"last_activity":{"predicates":["sioc:last_activity_date"],"datatype":"xsd:dateTime","callback":"date_iso8601"}},"path":{"pathauto":"1"},"cid":"0","last_comment_timestamp":"1475244707","last_comment_name":null,"last_comment_uid":"19331","comment_count":"0","name":"Thomas Schiendorfer","picture":"0","data":"a:2:{s:17:\"mimemail_textonly\";i:0;s:7:\"overlay\";i:1;}"},"15250":{"vid":"15251","uid":"19331","title":"5-Spr-I-A1-Anschluss","log":"","status":"1","comment":"1","promote":"0","sticky":"0","ds_switch":"","nid":"15250","type":"course_tabs","language":"de","created":"1475244760","changed":"1479458341","tnid":"0","translate":"0","revision_timestamp":"1479458341","revision_uid":"19331","body":{"und":[{"value":"<ul>\r\n\t<li><a href=\"\/node\/14953\" target=\"_blank\">Italienisch A2<\/a><\/li>\r\n<\/ul>\r\n","summary":"","format":"html","safe_value":"<ul><li><a href=\"\/node\/14953\" target=\"_blank\">Italienisch A2<\/a><\/li>\n<\/ul>","safe_summary":""}]},"field_course":{"und":[{"target_id":"14951"}]},"field_tab_title":{"und":[{"value":"Anschlussausbildungen","format":null,"safe_value":"Anschlussausbildungen"}]},"rdf_mapping":{"rdftype":["sioc:Item","foaf:Document"],"title":{"predicates":["dc:title"]},"created":{"predicates":["dc:date","dc:created"],"datatype":"xsd:dateTime","callback":"date_iso8601"},"changed":{"predicates":["dc:modified"],"datatype":"xsd:dateTime","callback":"date_iso8601"},"body":{"predicates":["content:encoded"]},"uid":{"predicates":["sioc:has_creator"],"type":"rel"},"name":{"predicates":["foaf:name"]},"comment_count":{"predicates":["sioc:num_replies"],"datatype":"xsd:integer"},"last_activity":{"predicates":["sioc:last_activity_date"],"datatype":"xsd:dateTime","callback":"date_iso8601"}},"path":{"pathauto":"1"},"cid":"0","last_comment_timestamp":"1475244760","last_comment_name":null,"last_comment_uid":"19331","comment_count":"0","name":"Thomas Schiendorfer","picture":"0","data":"a:2:{s:17:\"mimemail_textonly\";i:0;s:7:\"overlay\";i:1;}"}}}